{
  "id": 254,
  "name": "イアソン",
  "false_name": null,
  "ascension_names": null,
  "klass": "Saber",
  "rarity": 1,
  "skills": [
    [
      {
        "slot": 1,
        "level": 1,
        "name": "求めし金羊の皮",
        "rank": "",
        "icon": 600
      }
    ],
    [
      {
        "slot": 2,
        "level": 1,
        "name": "虎口にて閃く",
        "rank": "A",
        "icon": 402
      }
    ],
    [
      {
        "slot": 3,
        "level": 1,
        "name": "友と征く遙かなる海路",
        "rank": "B++",
        "icon": 300
      }
    ]
  ],
  "append_skills": [
    [
      {
        "slot": 1,
        "level": 1,
        "name": "追撃技巧向上",
        "rank": "",
        "icon": 301
      }
    ],
    [
      {
        "slot": 2,
        "level": 1,
        "name": "魔力装填",
        "rank": "",
        "icon": 601
      }
    ],
    [
      {
        "slot": 3,
        "level": 1,
        "name": "対キャスター攻撃適性",
        "rank": "",
        "icon": 300
      }
    ],
    [
      {
        "slot": 4,
        "level": 1,
        "name": "特撃技巧向上",
        "rank": "",
        "icon": 303
      }
    ],
    [
      {
        "slot": 5,
        "level": 1,
        "name": "スキル再装填",
        "rank": "",
        "icon": 613
      }
    ]
  ],
  "costumes": [],
  "ascension_resources": [
    {
      "qp": 10000,
      "items": [
        {
          "name": "セイバーピース",
          "piece": 2
        }
      ]
    },
    {
      "qp": 30000,
      "items": [
        {
          "name": "セイバーピース",
          "piece": 4
        },
        {
          "name": "竜の牙",
          "piece": 6
        }
      ]
    },
    {
      "qp": 90000,
      "items": [
        {
          "name": "セイバーモニュメント",
          "piece": 2
        },
        {
          "name": "英雄の証",
          "piece": 10
        },
        {
          "name": "鳳凰の羽根",
          "piece": 2
        }
      ]
    },
    {
      "qp": 300000,
      "items": [
        {
          "name": "セイバーモニュメント",
          "piece": 4
        },
        {
          "name": "鳳凰の羽根",
          "piece": 3
        },
        {
          "name": "原初の産毛",
          "piece": 3
        }
      ]
    }
  ],
  "skill_resources": [
    {
      "qp": 10000,
      "items": [
        {
          "name": "剣の輝石",
          "piece": 2
        }
      ]
    },
    {
      "qp": 20000,
      "items": [
        {
          "name": "剣の輝石",
          "piece": 4
        }
      ]
    },
    {
      "qp": 60000,
      "items": [
        {
          "name": "剣の魔石",
          "piece": 2
        }
      ]
    },
    {
      "qp": 80000,
      "items": [
        {
          "name": "剣の魔石",
          "piece": 4
        },
        {
          "name": "英雄の証",
          "piece": 5
        }
      ]
    },
    {
      "qp": 200000,
      "items": [
        {
          "name": "剣の秘石",
          "piece": 2
        },
        {
          "name": "英雄の証",
          "piece": 10
        }
      ]
    },
    {
      "qp": 250000,
      "items": [
        {
          "name": "剣の秘石",
          "piece": 4
        },
        {
          "name": "竜の牙",
          "piece": 4
        }
      ]
    },
    {
      "qp": 500000,
      "items": [
        {
          "name": "竜の牙",
          "piece": 8
        },
        {
          "name": "巨人の指輪",
          "piece": 2
        }
      ]
    },
    {
      "qp": 600000,
      "items": [
        {
          "name": "巨人の指輪",
          "piece": 6
        },
        {
          "name": "真理の卵",
          "piece": 4
        }
      ]
    },
    {
      "qp": 1000000,
      "items": [
        {
          "name": "伝承結晶",
          "piece": 1
        }
      ]
    }
  ],
  "append_skill_resources": [
    {
      "qp": 10000,
      "items": [
        {
          "name": "剣の輝石",
          "piece": 2
        }
      ]
    },
    {
      "qp": 20000,
      "items": [
        {
          "name": "剣の輝石",
          "piece": 4
        }
      ]
    },
    {
      "qp": 60000,
      "items": [
        {
          "name": "剣の魔石",
          "piece": 2
        }
      ]
    },
    {
      "qp": 80000,
      "items": [
        {
          "name": "剣の魔石",
          "piece": 4
        },
        {
          "name": "鳳凰の羽根",
          "piece": 2
        }
      ]
    },
    {
      "qp": 200000,
      "items": [
        {
          "name": "剣の秘石",
          "piece": 2
        },
        {
          "name": "鳳凰の羽根",
          "piece": 3
        }
      ]
    },
    {
      "qp": 250000,
      "items": [
        {
          "name": "剣の秘石",
          "piece": 4
        },
        {
          "name": "原初の産毛",
          "piece": 1
        }
      ]
    },
    {
      "qp": 500000,
      "items": [
        {
          "name": "原初の産毛",
          "piece": 2
        },
        {
          "name": "追憶の貝殻",
          "piece": 2
        }
      ]
    },
    {
      "qp": 600000,
      "items": [
        {
          "name": "追憶の貝殻",
          "piece": 6
        },
        {
          "name": "蛮神の心臓",
          "piece": 4
        }
      ]
    },
    {
      "qp": 1000000,
      "items": [
        {
          "name": "伝承結晶",
          "piece": 1
        }
      ]
    }
  ]
}
